{
  "type": "FeatureCollection",
  "features": [
    {
      "type": "Feature",
      "geometry": {
        "type": "Point",
        "coordinates": [-79.93345, 40.46111]
      },
      "properties": {
          "title": "Mapbox",
          "description": "Washington, D.C."
        }
    },
    {
      "type": "Feature",
      "geometry": {
        "type": "Point",
        "coordinates": [-122.414, 37.776]
      },
      "properties": {
          "title": "Mapbox",
          "description": "San Francisco, California"
        }
    }
  ]
}